drxhello/__init__.py
drxhello/module.py
drxhello-0.0.2.dist-info/METADATA
drxhello-0.0.2.dist-info/WHEEL
drxhello-0.0.2.dist-info/top_level.txt
drxhello-0.0.2.dist-info/RECORD
