Metadata-Version: 2.1
Name: drxhello
Version: 0.0.2
Summary: drxhello
Home-page: https://github.com/drewxa/pypi-test
Download-URL: https://pypi.org/project/drxhello/
Author: drewxa
Author-email: drewxa@gmail.com
License: MIT
Keywords: helloworld,drewxa
Platform: UNKNOWN
Requires-Dist: request (>2.10)
